smpldta/__init__.py
smpldta/gen_code.py
smpldta/gen_gifs.py
smpldta/gen_images.py
smpldta/gen_json.py
smpldta/gen_pdfs.py
smpldta/gen_text.py
smpldta/gen_videos.py
smpldta/setup_logger.py
smpldta/utils.py
smpldta-0.2.1.dist-info/licenses/LICENSE
smpldta-0.2.1.dist-info/METADATA
smpldta-0.2.1.dist-info/WHEEL
smpldta-0.2.1.dist-info/entry_points.txt
smpldta-0.2.1.dist-info/top_level.txt
smpldta-0.2.1.dist-info/RECORD
