Metadata-Version: 2.4
Name: smpldta
Version: 0.2.1
Summary: Fetch sample data like images, videos, code, GIFs, text, and JSON files.
Home-page: https://github.com/parteekahlawat/smpldta
Author: Parteek
Author-email: Parteek <prateekahlawat1223@gmail.com>
License: MIT License
Project-URL: Homepage, https://github.com/parteekahlawat/smpldta
Classifier: Programming Language :: Python :: 3
Classifier: Operating System :: OS Independent
Requires-Python: >=3.0
License-File: LICENSE
Requires-Dist: requests
Requires-Dist: reportlab
Dynamic: author
Dynamic: home-page
Dynamic: license-file
Dynamic: requires-python
